cap_cake/__init__.py
cap_cake/capcake.py
capac-0.0.2.dist-info/LICENSE
capac-0.0.2.dist-info/METADATA
capac-0.0.2.dist-info/WHEEL
capac-0.0.2.dist-info/top_level.txt
capac-0.0.2.dist-info/RECORD
